akeyless_cloud_id/__init__.py
akeyless_cloud_id/cloud_id.py
akeyless_cloud_id-0.3.0.dist-info/licenses/LICENSE
akeyless_cloud_id-0.3.0.dist-info/METADATA
akeyless_cloud_id-0.3.0.dist-info/WHEEL
akeyless_cloud_id-0.3.0.dist-info/top_level.txt
akeyless_cloud_id-0.3.0.dist-info/RECORD
