Metadata-Version: 2.4
Name: akeyless_cloud_id
Version: 0.3.0
Summary: AKEYLESS Cloud ID Retriever
Home-page: https://www.akeyless.io/
Author: Akeyless Security
Author-email: support@akeyless.io
License: Apache 2.0
Keywords: AKEYLESS Cloud ID
Classifier: Intended Audience :: Developers
Classifier: Natural Language :: English
Classifier: License :: OSI Approved :: Apache Software License
Classifier: Operating System :: OS Independent
Classifier: Programming Language :: Python
Classifier: Programming Language :: Python :: 3
Classifier: Programming Language :: Python :: 3.5
Classifier: Programming Language :: Python :: 3.6
Classifier: Programming Language :: Python :: 3.7
Classifier: Topic :: Security
License-File: LICENSE
Requires-Dist: urllib3>=1.15
Requires-Dist: requests
Provides-Extra: aws
Requires-Dist: boto3; extra == "aws"
Provides-Extra: gcp
Requires-Dist: google-auth; extra == "gcp"
Provides-Extra: azure
Requires-Dist: azure-identity; extra == "azure"
Dynamic: author
Dynamic: author-email
Dynamic: classifier
Dynamic: description
Dynamic: description-content-type
Dynamic: home-page
Dynamic: keywords
Dynamic: license
Dynamic: license-file
Dynamic: provides-extra
Dynamic: requires-dist
Dynamic: summary
